rdb2rdf/dm.py
rdb2rdf/__init__.py
rdb2rdf/_common.py
rdb2rdf/stores.py
rdb2rdf/tests/__init__.py
rdb2rdf-0.1.3.dist-info/METADATA
rdb2rdf-0.1.3.dist-info/entry_points.txt
rdb2rdf-0.1.3.dist-info/RECORD
rdb2rdf-0.1.3.dist-info/top_level.txt
rdb2rdf-0.1.3.dist-info/namespace_packages.txt
rdb2rdf-0.1.3.dist-info/WHEEL
rdb2rdf-0.1.3.dist-info/metadata.json
rdb2rdf-0.1.3.dist-info/DESCRIPTION.rst
