Metadata-Version: 2.0
Name: rdb2rdf
Version: 0.1.3
Summary: PyRDB2RDF
Home-page: UNKNOWN
Author: Ivan D Vasin
Author-email: nisavid@gmail.com
License: GNU LESSER GENERAL PUBLIC LICENSE
Requires-Dist: rdflib
Requires-Dist: spruce-collections
Requires-Dist: spruce-datetime
Requires-Dist: spruce-iri
Requires-Dist: spruce-types
Requires-Dist: sqlalchemy (>=0.9.1)
